mcp_wake_on_lan/__init__.py
mcp_wake_on_lan/__main__.py
mcp_wake_on_lan/server.py
mcp_wake_on_lan-0.1.0.dist-info/METADATA
mcp_wake_on_lan-0.1.0.dist-info/WHEEL
mcp_wake_on_lan-0.1.0.dist-info/entry_points.txt
mcp_wake_on_lan-0.1.0.dist-info/licenses/LICENSE
mcp_wake_on_lan-0.1.0.dist-info/RECORD
