Metadata-Version: 2.4
Name: mcp-wake-on-lan
Version: 0.1.0
Summary: A simple MCP server that implements Wake-on-LAN functionality to remotely wake up network devices.
Author: lkanyun.
Maintainer-email: lkanyun <zshunshun2018@gmail.com>
License: MIT
License-File: LICENSE
Keywords: automation,llm,mcp,wake_on_lan
Classifier: Development Status :: 4 - Beta
Classifier: Intended Audience :: Developers
Classifier: License :: OSI Approved :: MIT License
Classifier: Programming Language :: Python :: 3
Classifier: Programming Language :: Python :: 3.11
Requires-Python: >=3.11
Requires-Dist: anyio>=4.5
Requires-Dist: click>=8.1.0
Requires-Dist: mcp
